<?xml version="1.0" encoding="utf-8"?>
<odoo>
    <record model="ir.actions.server" id="action_pass_analytic_account">
        <field name="name">Assign Analytic Account</field>
        <field name="model_id" ref="purchase.model_purchase_order"/>
        <field name="binding_model_id" ref="purchase.model_purchase_order"/>
        <field name="binding_view_types">list,form</field>
        <field name="state">code</field>
        <field name="code">
record._onchange_job_number()
        </field>
    </record>
</odoo>
